bbbscrape/__init__.py
bbbscrape/main.py
bbbscrape/version.py
bbb_scrape-1.0.4.dist-info/LICENSE
bbb_scrape-1.0.4.dist-info/METADATA
bbb_scrape-1.0.4.dist-info/WHEEL
bbb_scrape-1.0.4.dist-info/entry_points.txt
bbb_scrape-1.0.4.dist-info/top_level.txt
bbb_scrape-1.0.4.dist-info/RECORD
