Metadata-Version: 2.1
Name: bbb-scrape
Version: 1.0.4
Summary: Scrape BBB meeting
Home-page: https://github.com/wallento/bbb-scrape
Author: Stefan Wallentowitz
Author-email: stefan.wallentowitz@hm.edu
License: UNKNOWN
Platform: UNKNOWN
Classifier: Programming Language :: Python :: 3
Classifier: License :: OSI Approved :: MIT License
Classifier: Operating System :: OS Independent
Requires-Python: >=3.5
Requires-Dist: requests
